agentfence/__init__.py
agentfence/connectors/__init__.py
agentfence/connectors/base_agent.py
agentfence/connectors/dialogflow_agent.py
agentfence/connectors/langgraph_agent.py
agentfence/connectors/openai_agent.py
agentfence/evaluators/__init__.py
agentfence/evaluators/base_evaluator.py
agentfence/evaluators/llm_evaluator.py
agentfence/evaluators/regex_evaluator.py
agentfence/probes/__init__.py
agentfence/probes/base_probe.py
agentfence/probes/data_extraction.py
agentfence/probes/harmful_language.py
agentfence/probes/instructions_leakage.py
agentfence/probes/jailbreak.py
agentfence/probes/prompt_injection.py
agentfence/probes/role_confusion.py
agentfence/probes/secret_leakage.py
agentfence/probes/tool_access.py
agentfence/result.py
agentfence/run_probes.py
agentfence-0.1.0.dist-info/LICENSE
agentfence-0.1.0.dist-info/METADATA
agentfence-0.1.0.dist-info/WHEEL
agentfence-0.1.0.dist-info/RECORD
