Metadata-Version: 2.1
Name: agentfence
Version: 0.1.0
Summary: A Python library for testing and identifying security vulnerabilities in AI agents.
Home-page: https://agentfence.ai
License: MIT
Keywords: AI security,agent security
Author: Haggai Shachar
Requires-Python: >=3.9,<3.13
Classifier: License :: OSI Approved :: MIT License
Classifier: Programming Language :: Python :: 3
Classifier: Programming Language :: Python :: 3.9
Classifier: Programming Language :: Python :: 3.10
Classifier: Programming Language :: Python :: 3.11
Classifier: Programming Language :: Python :: 3.12
Provides-Extra: dialogflow
Requires-Dist: langchain (>=0.3.20,<0.4.0)
Requires-Dist: langchain-openai (>=0.3.7,<0.4.0)
Requires-Dist: langchain_community (>=0.3.19,<0.4.0)
Requires-Dist: langgraph (>=0.3.5,<0.4.0)
Requires-Dist: python-dotenv (>=1.0.1,<2.0.0)
Requires-Dist: requests (>=2.32.3,<3.0.0)
Project-URL: Repository, https://github.com/agentfence/agentfence
